phenoscope/__init__.py
phenoscope/abstract/__init__.py
phenoscope/abstract/_docstring_metaclass.py
phenoscope/abstract/_feature_extractor.py
phenoscope/abstract/_image_operation.py
phenoscope/abstract/_image_preprocessor.py
phenoscope/abstract/_image_transformer.py
phenoscope/abstract/_map_modifier.py
phenoscope/abstract/_object_detector.py
phenoscope/abstract/_threshold_detector.py
phenoscope/core/__init__.py
phenoscope/core/_grid_image.py
phenoscope/core/_image.py
phenoscope/core/_imread.py
phenoscope/core/accessors/__init__.py
phenoscope/core/accessors/_grid_accessor.py
phenoscope/core/accessors/_hsv_accessor.py
phenoscope/core/accessors/_image_array_accessor.py
phenoscope/core/accessors/_image_enh_matrix_accessor.py
phenoscope/core/accessors/_image_matrix_accessor.py
phenoscope/core/accessors/_image_objects_accessor.py
phenoscope/core/accessors/_measurement_accessor.py
phenoscope/core/accessors/_metadata_accessor.py
phenoscope/core/accessors/_object_map_accessor.py
phenoscope/core/accessors/_object_mask_accessor.py
phenoscope/core/handlers/__init__.py
phenoscope/core/handlers/_image_grid_handler.py
phenoscope/core/handlers/_image_handler.py
phenoscope/core/handlers/_image_hsv_handler.py
phenoscope/data/__init__.py
phenoscope/data/_sample_image_data.py
phenoscope/detection/__init__.py
phenoscope/detection/_otsu_detector.py
phenoscope/detection/_triangle_detector.py
phenoscope/grid/__init__.py
phenoscope/grid/_grid_aligner.py
phenoscope/grid/_grid_apply.py
phenoscope/grid/_grid_linreg_stats_extractor.py
phenoscope/grid/_grid_oversized_object_remover.py
phenoscope/grid/_linreg_residual_outlier_modifier.py
phenoscope/grid/_min_residual_error_modifier.py
phenoscope/grid/_object_spread_extractor.py
phenoscope/grid/_optimal_center_grid_setter.py
phenoscope/grid/abstract/__init__.py
phenoscope/grid/abstract/_grid_feature_extractor.py
phenoscope/grid/abstract/_grid_finder.py
phenoscope/grid/abstract/_grid_map_modifier.py
phenoscope/grid/abstract/_grid_morpher.py
phenoscope-0.5.1.dist-info/LICENSE
phenoscope-0.5.1.dist-info/METADATA
phenoscope-0.5.1.dist-info/WHEEL
phenoscope-0.5.1.dist-info/top_level.txt
phenoscope-0.5.1.dist-info/RECORD
