Metadata-Version: 2.2
Name: phenoscope
Version: 0.5.1
Summary: An image processing framework created for Ex-FAB NSF BioFoundry that aims to streamline the development of image processing pipelines for images analysis of phenotypes.
Author-email: Alexander Nguyen <xander-git@protonmail.com>
Project-URL: Repository, https://github.com/Xander-git/PhenoScope
Classifier: Development Status :: 2 - Pre-Alpha
Classifier: License :: OSI Approved :: GNU General Public License v3 (GPLv3)
Classifier: Natural Language :: English
Classifier: Programming Language :: Python
Classifier: Programming Language :: Python :: 3.12
Requires-Python: ~=3.12
License-File: LICENSE
Requires-Dist: pandas
Requires-Dist: numpy
Requires-Dist: seaborn
Requires-Dist: scikit-image
Requires-Dist: scikit-learn
Requires-Dist: scipy
Requires-Dist: opencv-python
Requires-Dist: h5py
Requires-Dist: mahotas
Requires-Dist: pillow
Provides-Extra: dev
Requires-Dist: pytest; extra == "dev"
Requires-Dist: pytest-cov; extra == "dev"
Requires-Dist: mypy; extra == "dev"
Requires-Dist: sphinx-autobuild; extra == "dev"
Requires-Dist: nbsphinx; extra == "dev"
Requires-Dist: ipykernel; extra == "dev"
Requires-Dist: jupyter; extra == "dev"
Requires-Dist: sphinx; extra == "dev"
Requires-Dist: sphinxcontrib-napoleon; extra == "dev"
Requires-Dist: sphinx-autodoc-typehints; extra == "dev"
Requires-Dist: sphinxawesome-theme; extra == "dev"
Requires-Dist: furo; extra == "dev"
Requires-Dist: pydata-sphinx-theme; extra == "dev"
Requires-Dist: sphinx-gallery; extra == "dev"
Requires-Dist: myst-nb; extra == "dev"
